{
  "project_info": {
    "project_number": "504168798401",
    "project_id": "fir-img-c7b90",
    "storage_bucket": "fir-img-c7b90.appspot.com"
  },
  "client": [
    {
      "client_info": {
        "mobilesdk_app_id": "1:504168798401:android:fd2b35e1cf0f83970d9c40",
        "android_client_info": {
          "package_name": "com.duck.firebaseimg"
        }
      },
      "oauth_client": [
        {
          "client_id": "504168798401-3ilivulu6sleskqjec6d8f4cp58jlr55.apps.googleusercontent.com",
          "client_type": 3
        }
      ],
      "api_key": [
        {
          "current_key": "AIzaSyA20BrAQIzlTqUEhZTp9NSndjdpgz4RuT0"
        }
      ],
      "services": {
        "appinvite_service": {
          "other_platform_oauth_client": [
            {
              "client_id": "504168798401-3ilivulu6sleskqjec6d8f4cp58jlr55.apps.googleusercontent.com",
              "client_type": 3
            }
          ]
        }
      }
    }
  ],
  "configuration_version": "1"
}